{
  "url": "https://www.leafly.com/strains/arjans-strawberry-haze",
  "name": "Strawberry Haze",
  "awards": [
    "1st prize at the Green House Very Important Smokers Panel in 2005"
  ],
  "effects": [
    "Energetic",
    "Talkative",
    "Uplifted"
  ],
  "flavors": [
    "Strawberry",
    "Sweet",
    "Berry"
  ],
  "lineage": [
    "Haze",
    "Northern Lights #5"
  ],
  "medical": [
    "Depression",
    "Stress",
    "Anxiety"
  ],
  "terpenes": [
    "Myrcene",
    "Ocimene",
    "Pinene"
  ],
  "grow_info": {
    "yield": "medium",
    "height": "tall",
    "difficulty": "easy",
    "flowering_time_weeks": 10
  },
  "cbd_percent": 1,
  "description": "Strawberry Haze, also known as \"Arjan's Strawberry Haze,\" was created by Arjan and introduced on the market in 2006. In 2005, Strawberry Haze won 1st prize at the Green House Very Important Smokers Panel. The buds of Strawberry Haze smell of strawberries and provide a sweet taste, which is heightened when roots are given free reign in soil. It is characterized as a tall plant with long branches. Strawberry Haze is a simple plant to grow and maintain, as it is known to be adaptable to humidity. Flowering time is approximately 10 weeks with a THC level up to 20% and CBD of 1.2%.",
  "thc_percent": 19,
  "rating_count": 199,
  "average_rating": 4.3,
  "classification": "Sativa"
}