{
  "url": "https://www.leafly.com/strains/legalized-og",
  "name": "Legalized OG",
  "awards": [],
  "effects": [
    "Relaxed",
    "Uplifted",
    "Focused"
  ],
  "flavors": [
    "Pine",
    "Fruity"
  ],
  "lineage": [
    "OG Kush"
  ],
  "medical": [
    "Depression",
    "Pain",
    "Stress"
  ],
  "terpenes": [
    "Limonene",
    "Myrcene",
    "Caryophyllene"
  ],
  "grow_info": {
    "yield": "medium",
    "height": "medium",
    "difficulty": "moderate",
    "flowering_time_weeks": null
  },
  "cbd_percent": null,
  "description": "Legalized OG is a popularized cut of the famous OG Kush. This strain’s flavor is piney with fruity nuances that some might describe as grape or berry. The effects set in immediately and envelop the body from the head down with a sedating buzz that lingers and weighs on the body. Legalized OG stays true to its OG roots and would be an ideal cut for patients seeking relief from chronic pain, nausea, or restlessness.",
  "thc_percent": 18,
  "rating_count": 21,
  "average_rating": 4.8,
  "classification": "Hybrid"
}