{
  "url": "https://www.leafly.com/strains/redneck-wedding",
  "name": "Redneck Wedding",
  "awards": [],
  "effects": [
    "Happy",
    "Giggly",
    "Energetic"
  ],
  "flavors": [
    "Cheese",
    "Blueberry",
    "Coffee"
  ],
  "lineage": [
    "GMO",
    "Trophy Wife"
  ],
  "medical": [
    "Anxiety",
    "Depression",
    "Cramps"
  ],
  "terpenes": [
    "Limonene",
    "Myrcene",
    "Caryophyllene"
  ],
  "grow_info": {
    "yield": "medium",
    "height": "medium",
    "difficulty": "moderate",
    "flowering_time_weeks": null
  },
  "cbd_percent": null,
  "description": "Redneck Wedding is a hybrid weed strain. Reviewers on Leafly say this strain makes them feel happy, giggly, and energetic. Redneck Wedding has 22% THC and 1% CBG. The dominant terpene in this strain is limonene.",
  "thc_percent": 22,
  "rating_count": 17,
  "average_rating": 4.6,
  "classification": "Hybrid"
}