{
  "url": "https://www.leafly.com/strains/strawberry",
  "name": "Strawberry",
  "awards": [],
  "effects": [
    "Uplifted",
    "Energetic",
    "Aroused"
  ],
  "flavors": [
    "Strawberry",
    "Sweet",
    "Berry"
  ],
  "lineage": [
    "Strawberries and Cream",
    "Strawberry Mochi"
  ],
  "medical": [
    "Stress",
    "Anxiety",
    "Depression"
  ],
  "terpenes": [
    "Myrcene",
    "Pinene",
    "Ocimene"
  ],
  "grow_info": {
    "yield": "medium",
    "height": "medium",
    "difficulty": "moderate",
    "flowering_time_weeks": 9
  },
  "cbd_percent": 1,
  "description": "Strawberry is a sativa marijuana strain originating from the Netherlands. This strain produces effects that are uplifting and relaxing. Strawberry is a popular choice for those prone to anxiety due to its stress-relieving qualities. Medical marijuana patients choose Strawberry for reducing physical and mental pain. Growers say this strain grows well both indoors and outdoors and has a 9 week flowering time.",
  "thc_percent": 18,
  "rating_count": 201,
  "average_rating": 4.3,
  "classification": "Sativa"
}